inu_net/__init__.py
inu_net/app.py
inu_net/const.py
inu_net/error.py
inu_net/tz.py
inu_net/hardware/__init__.py
inu_net/hardware/pir.py
inu_net/hardware/relay.py
inu_net/hardware/sonar.py
inu_net/hardware/switch.py
inu_net/hardware/light/__init__.py
inu_net/hardware/light/bh1750.py
inu_net/hardware/light/veml6030.py
inu_net/hardware/robotics/__init__.py
inu_net/hardware/robotics/actuator.py
inu_net/hardware/robotics/apa102.py
inu_net/hardware/robotics/colour.py
inu_net/hardware/robotics/control/__init__.py
inu_net/hardware/robotics/control/actuator.py
inu_net/hardware/robotics/control/common.py
inu_net/hardware/robotics/control/lights.py
inu_net/lib/__init__.py
inu_net/lib/switch.py
inu_net/schema/__init__.py
inu_net/schema/command.py
inu_net/schema/status.py
inu_net/schema/settings/__init__.py
inu_net/schema/settings/robotics.py
inu_net/schema/settings/sensors.py
inu_net/updater/__init__.py
inu_net/util/__init__.py
inu_net/util/bootstrap.py
inu_net/util/build.py
inu_net/util/monitor.py
inu_net/util/settings.py
inu_net/util/toggle.py
inu_net-1.43.1.dist-info/METADATA
inu_net-1.43.1.dist-info/WHEEL
inu_net-1.43.1.dist-info/top_level.txt
inu_net-1.43.1.dist-info/RECORD
