Metadata-Version: 2.1
Name: inu-net
Version: 1.43.1
Summary: The Inu IoT framework
Home-page: https://github.com/jordonsc/inu-py
Author: Jordon Scott
Author-email: jordonsc@gmail.com
License: MIT
Platform: UNKNOWN
Requires-Dist: micro-nats
